binview/__init__.py
binview/cli.py
binview/dump.py
binview-0.1.3.dist-info/LICENSE
binview-0.1.3.dist-info/METADATA
binview-0.1.3.dist-info/WHEEL
binview-0.1.3.dist-info/entry_points.txt
binview-0.1.3.dist-info/top_level.txt
binview-0.1.3.dist-info/RECORD
